redcaplite/__init__.py
redcaplite/redcap.py
redcaplite/api/__init__.py
redcaplite/api/arm.py
redcaplite/api/dag.py
redcaplite/api/event.py
redcaplite/api/field_names.py
redcaplite/api/file.py
redcaplite/api/file_repository.py
redcaplite/api/form_event_mapping.py
redcaplite/api/instrument.py
redcaplite/api/log.py
redcaplite/api/metadata.py
redcaplite/api/pdf.py
redcaplite/api/project.py
redcaplite/api/record.py
redcaplite/api/repeating_forms_events.py
redcaplite/api/report.py
redcaplite/api/survey.py
redcaplite/api/user.py
redcaplite/api/user_dag_mapping.py
redcaplite/api/user_role.py
redcaplite/api/user_role_mapping.py
redcaplite/api/utils.py
redcaplite/api/version.py
redcaplite/http/__init__.py
redcaplite/http/client.py
redcaplite/http/error.py
redcaplite/http/handler.py
redcaplite-1.4.2.dist-info/METADATA
redcaplite-1.4.2.dist-info/WHEEL
redcaplite-1.4.2.dist-info/licenses/LICENSE
redcaplite-1.4.2.dist-info/RECORD
