Metadata-Version: 2.4
Name: redcaplite
Version: 1.4.2
Summary: A Lightweight Python Client for REDCap
Project-URL: Homepage, https://github.com/jubilee2/RedcapLite
Project-URL: Issues, https://github.com/jubilee2/RedcapLite/issues
Author-email: Jubilee Tan <jubilee2@gmail.com>
License-File: LICENSE
Classifier: License :: OSI Approved :: MIT License
Classifier: Operating System :: OS Independent
Classifier: Programming Language :: Python :: 3
Requires-Python: >=3.8
Requires-Dist: pandas
Requires-Dist: requests
